pymagcore/__init__.py
pymagcore/api.py
pymagcore-0.1.0.dist-info/LICENSE
pymagcore-0.1.0.dist-info/METADATA
pymagcore-0.1.0.dist-info/WHEEL
pymagcore-0.1.0.dist-info/top_level.txt
pymagcore-0.1.0.dist-info/RECORD
